setup.py
InflationIO/InflationIO.py
InflationIO/__init__.py
InflationIO.egg-info/PKG-INFO
InflationIO.egg-info/SOURCES.txt
InflationIO.egg-info/dependency_links.txt
InflationIO.egg-info/top_level.txt