Metadata-Version: 1.0
Name: InflationIO
Version: 1.0.0
Summary: calculates inflation over investment history
Home-page: UNKNOWN
Author: UNKNOWN
Author-email: UNKNOWN
License: UNKNOWN
Platform: UNKNOWN
